xia_openapi_flask/__init__.py
xia_openapi_flask/openapi.cpython-310-darwin.so
xia_openapi_flask-0.0.3.dist-info/LICENSE.txt
xia_openapi_flask-0.0.3.dist-info/METADATA
xia_openapi_flask-0.0.3.dist-info/WHEEL
xia_openapi_flask-0.0.3.dist-info/top_level.txt
xia_openapi_flask-0.0.3.dist-info/RECORD
