Metadata-Version: 2.1
Name: xia-openapi-flask
Version: 0.0.3
Summary: X-I-A
Home-page: https://develop.x-i-a.com/docs/xia-openapi-flask/0.0.3/index.html
Author: X-I-A
Author-email: admin@x-i-a.com
Requires-Python: >=3.9
License-File: LICENSE.txt
Requires-Dist: Flask
Requires-Dist: xia-compiler-openapi
